Metadata-Version: 2.1
Name: pythonal10
Version: 1.0.1
Summary: A package that prints my name
Home-page: UNKNOWN
Author: Guido Xhindoli
Author-email: <mail@gmail.com>
License: UNKNOWN
Keywords: pythonal,pythonal10,name,sda
Platform: UNKNOWN
Classifier: Development Status :: 1 - Planning
Classifier: Intended Audience :: Developers
Classifier: Programming Language :: Python :: 3
Classifier: Operating System :: Unix
Classifier: Operating System :: MacOS :: MacOS X
Classifier: Operating System :: Microsoft :: Windows
